redirectwolf.py
redirectwolf-1.0.0.dist-info/licenses/LICENSE
redirectwolf-1.0.0.dist-info/METADATA
redirectwolf-1.0.0.dist-info/WHEEL
redirectwolf-1.0.0.dist-info/entry_points.txt
redirectwolf-1.0.0.dist-info/top_level.txt
redirectwolf-1.0.0.dist-info/RECORD
