Metadata-Version: 2.4
Name: redirectwolf
Version: 1.0.0
Summary: Asynchronous Open Redirect Vulnerability Scanner
Home-page: https://github.com/nkbeast/RedirectWolf
Author: NK
Author-email: naveenbeastyt@gmail.com
Classifier: Programming Language :: Python :: 3
Classifier: License :: OSI Approved :: MIT License
Classifier: Operating System :: OS Independent
Requires-Python: >=3.8
License-File: LICENSE
Requires-Dist: httpx>=0.24.0
Requires-Dist: click>=8.1
Requires-Dist: PyYAML>=6.0
Dynamic: author
Dynamic: author-email
Dynamic: classifier
Dynamic: home-page
Dynamic: license-file
Dynamic: requires-dist
Dynamic: requires-python
Dynamic: summary
